<?xml version="1.1" encoding="UTF-8" standalone="no"?>
<databaseChangeLog xmlns="http://www.liquibase.org/xml/ns/dbchangelog" xmlns:ext="http://www.liquibase.org/xml/ns/dbchangelog-ext" xmlns:xsi="http://www.w3.org/2001/XMLSchema-instance" xsi:schemaLocation="http://www.liquibase.org/xml/ns/dbchangelog-ext http://www.liquibase.org/xml/ns/dbchangelog/dbchangelog-ext.xsd http://www.liquibase.org/xml/ns/dbchangelog http://www.liquibase.org/xml/ns/dbchangelog/dbchangelog-3.5.xsd">
    <changeSet author="Pravitha.Nair" id="1522834756004-1">
        <createTable tableName="user_details">
            <column name="user_id" type="BIGINT">
                <constraints nullable="false" unique="true" primaryKey="true"/>
            </column>
            <column name="user_name" type="VARCHAR(10)">
                <constraints nullable="false"/>
            </column>
        </createTable>
    </changeSet>
    <changeSet author="Pravitha.Nair" id="1522834756004-2">
        <createTable tableName="course_details">
            <column name="user_id" type="BIGINT">
                <constraints nullable="false" primaryKey="true"/>
            </column>
            <column name="course_id" type="BIGINT">
                <constraints nullable="false" primaryKey="true"/>
            </column>
            <column name="course_name" type="VARCHAR(10)">
                <constraints nullable="false"/>
            </column>
            <column defaultValueComputed="now()" name="register_date" type="DATE">
                <constraints nullable="false"/>
            </column>
        </createTable>
    </changeSet>
    <changeSet author="Pravitha.Nair" id="1522834756004-5">
        <addForeignKeyConstraint baseColumnNames="user_id" baseTableName="course_details" constraintName="course_details_fk" deferrable="false" initiallyDeferred="false" onDelete="NO ACTION" onUpdate="NO ACTION" referencedColumnNames="user_id" referencedTableName="user_details"/>
    </changeSet>
</databaseChangeLog>
